{
    "key": "group_60b2076acb8ce",
    "title": "Events",
    "fields": [
        {
            "key": "field_60b4eed13041a",
            "label": "Featured Event",
            "name": "event-featured",
            "type": "checkbox",
            "instructions": "",
            "required": 0,
            "conditional_logic": 0,
            "wrapper": {
                "width": "",
                "class": "",
                "id": ""
            },
            "choices": {
                "yes": "Yes"
            },
            "allow_custom": 0,
            "default_value": [],
            "layout": "vertical",
            "toggle": 0,
            "return_format": "value",
            "save_custom": 0
        },
        {
            "key": "field_60b20770730fc",
            "label": "Start Date",
            "name": "event-start-date",
            "type": "date_picker",
            "instructions": "",
            "required": 1,
            "conditional_logic": 0,
            "wrapper": {
                "width": "",
                "class": "",
                "id": ""
            },
            "display_format": "d-m-Y",
            "return_format": "Ymd",
            "first_day": 1
        },
        {
            "key": "field_60b20800730fd",
            "label": "End Date",
            "name": "event-end-date",
            "type": "date_picker",
            "instructions": "",
            "required": 0,
            "conditional_logic": 0,
            "wrapper": {
                "width": "",
                "class": "",
                "id": ""
            },
            "display_format": "d-m-Y",
            "return_format": "Ymd",
            "first_day": 1
        },
        {
            "key": "field_60b4ec1d7b814",
            "label": "All day event",
            "name": "event-all-day",
            "type": "checkbox",
            "instructions": "",
            "required": 0,
            "conditional_logic": 0,
            "wrapper": {
                "width": "",
                "class": "",
                "id": ""
            },
            "choices": {
                "yes": "Yes"
            },
            "allow_custom": 0,
            "default_value": [],
            "layout": "vertical",
            "toggle": 0,
            "return_format": "value",
            "save_custom": 0
        },
        {
            "key": "field_60b2084373100",
            "label": "Start Time",
            "name": "event-start-time",
            "type": "time_picker",
            "instructions": "",
            "required": 0,
            "conditional_logic": [
                [
                    {
                        "field": "field_60b4ec1d7b814",
                        "operator": "==empty"
                    }
                ]
            ],
            "wrapper": {
                "width": "",
                "class": "",
                "id": ""
            },
            "display_format": "g:i a",
            "return_format": "g:i a"
        },
        {
            "key": "field_60b2087373101",
            "label": "End Time",
            "name": "event-end-time",
            "type": "time_picker",
            "instructions": "",
            "required": 0,
            "conditional_logic": [
                [
                    {
                        "field": "field_60b4ec1d7b814",
                        "operator": "==empty"
                    }
                ]
            ],
            "wrapper": {
                "width": "",
                "class": "",
                "id": ""
            },
            "display_format": "g:i a",
            "return_format": "g:i a"
        },
        {
            "key": "field_60b208b773102",
            "label": "Cost",
            "name": "event-cost",
            "type": "number",
            "instructions": "",
            "required": 0,
            "conditional_logic": 0,
            "wrapper": {
                "width": "",
                "class": "",
                "id": ""
            },
            "default_value": "",
            "placeholder": "",
            "prepend": "$",
            "append": "",
            "min": "",
            "max": "",
            "step": ""
        },
        {
            "key": "field_60b4ea789790b",
            "label": "Teaser",
            "name": "event-teaser",
            "type": "textarea",
            "instructions": "",
            "required": 0,
            "conditional_logic": 0,
            "wrapper": {
                "width": "",
                "class": "",
                "id": ""
            },
            "default_value": "",
            "placeholder": "",
            "maxlength": "",
            "rows": "",
            "new_lines": ""
        },
        {
            "key": "field_60d9d2a4cc0fc",
            "label": "Thumbnail",
            "name": "event-thumbnail",
            "type": "image",
            "instructions": "Dimensions - 240 width, 135 height (pixels).\r\nMax file size - 100 KB.\r\nFile types - .jpg, .jpeg",
            "required": 1,
            "conditional_logic": 0,
            "wrapper": {
                "width": "",
                "class": "",
                "id": ""
            },
            "return_format": "array",
            "preview_size": "medium",
            "library": "all",
            "min_width": 240,
            "min_height": 135,
            "min_size": "",
            "max_width": 240,
            "max_height": 135,
            "max_size": "0.1",
            "mime_types": ".jpg, .jpeg"
        }
    ],
    "location": [
        [
            {
                "param": "post_type",
                "operator": "==",
                "value": "post"
            }
        ]
    ],
    "menu_order": 0,
    "position": "normal",
    "style": "default",
    "label_placement": "top",
    "instruction_placement": "label",
    "hide_on_screen": [
        "the_content"
    ],
    "active": 1,
    "description": "",
    "modified": 1642873757
}